zacrosio/__init__.py
zacrosio/input_functions.py
zacrosio/kmc_job.py
zacrosio-1.0.dist-info/LICENSE.txt
zacrosio-1.0.dist-info/METADATA
zacrosio-1.0.dist-info/WHEEL
zacrosio-1.0.dist-info/top_level.txt
zacrosio-1.0.dist-info/RECORD
