Metadata-Version: 2.1
Name: zacrosio
Version: 1.0
Summary: A collective of tools for the preparation of input files for ZACROS
Home-page: https://github.com/hprats/ZacrosIO
Download-URL: https://github.com/hprats/ZacrosIO/archive/refs/tags/v1.0.tar.gz
Author: Hector Prats Garcia
Author-email: hpratsgarcia@gmail.com
Keywords: python,chemistry,KMC,ZACROS
License-File: LICENSE.txt
Requires-Dist: pandas
Requires-Dist: scipy
